MANIFEST.in
README.md
README.txt
setup.py
graphdat/__init__.py
graphdat/agent.py
graphdat/dotdictionary.py
graphdat/metric.py
graphdat/wrapper.py
graphdat.egg-info/PKG-INFO
graphdat.egg-info/SOURCES.txt
graphdat.egg-info/dependency_links.txt
graphdat.egg-info/requires.txt
graphdat.egg-info/top_level.txt