Metadata-Version: 1.0
Name: graphdat
Version: 2.2
Summary: Graphdat instrumentation module
Home-page: http:/www.graphdat.com
Author: Graphdat
Author-email: support@graphdat.com
License: Apache License 2.0
Platform: UNKNOWN
